[
  {
    "id": "MII181401",
    "type": "Casa circondariale",
    "municipality": "Milano",
    "region": "Lombardia",
    "suicides": 1,
    "attemptedSuicides": 73,
    "selfHarm": 1182,
    "regulatoryRooms": 182,
    "nonRegulatoryRooms": 0,
    "totalPrisoners": 378,
    "overcrowdingAbsolute": 196,
    "overcrowdingPercent": 107.69,
    "expectedPolice": 149,
    "realPolice": 136,
    "differenceInPoliceNumbers": 13,
    "top30SelfHarm": true,
    "top30Suicides": true
  },
  {
    "id": "MII180465",
    "type": "Casa circondariale",
    "municipality": "Bologna",
    "region": "Emilia Romagna",
    "suicides": 2,
    "attemptedSuicides": 55,
    "selfHarm": 293,
    "regulatoryRooms": 136,
    "nonRegulatoryRooms": 5,
    "totalPrisoners": 189,
    "overcrowdingAbsolute": 53,
    "overcrowdingPercent": 38.97,
    "expectedPolice": 231,
    "realPolice": 201,
    "differenceInPoliceNumbers": 30,
    "top30SelfHarm": true,
    "top30Suicides": true
  },
  {
    "id": "MII182339",
    "type": "Casa circondariale",
    "municipality": "Torino",
    "region": "Piemonte",
    "suicides": 2,
    "attemptedSuicides": 51,
    "selfHarm": 174,
    "regulatoryRooms": 89,
    "nonRegulatoryRooms": 7,
    "totalPrisoners": 113,
    "overcrowdingAbsolute": 24,
    "overcrowdingPercent": 26.97,
    "expectedPolice": 125,
    "realPolice": 119,
    "differenceInPoliceNumbers": 6,
    "top30SelfHarm": true,
    "top30Suicides": true
  },
  {
    "id": "MII181115",
    "type": "Casa di reclusìone",
    "municipality": "Parma",
    "region": "Emilia Romagna",
    "suicides": 3,
    "attemptedSuicides": 43,
    "selfHarm": 296,
    "regulatoryRooms": 106,
    "nonRegulatoryRooms": 11,
    "totalPrisoners": 170,
    "overcrowdingAbsolute": 64,
    "overcrowdingPercent": 60.38,
    "expectedPolice": 205,
    "realPolice": 159,
    "differenceInPoliceNumbers": 46,
    "top30SelfHarm": true,
    "top30Suicides": true
  },
  {
    "id": "MII173747",
    "type": "Casa circondariale",
    "municipality": "Lecce",
    "region": "Puglia",
    "suicides": 1,
    "attemptedSuicides": 43,
    "selfHarm": 174,
    "regulatoryRooms": 1170,
    "nonRegulatoryRooms": 113,
    "totalPrisoners": 1566,
    "overcrowdingAbsolute": 396,
    "overcrowdingPercent": 33.85,
    "expectedPolice": 330,
    "realPolice": 261,
    "differenceInPoliceNumbers": 69,
    "top30SelfHarm": true,
    "top30Suicides": true
  },
  {
    "id": "MII173688",
    "type": "Casa circondariale",
    "municipality": "Sassari",
    "region": "Sardegna",
    "suicides": 2,
    "attemptedSuicides": 42,
    "selfHarm": 0,
    "regulatoryRooms": 628,
    "nonRegulatoryRooms": 62,
    "totalPrisoners": 1085,
    "overcrowdingAbsolute": 457,
    "overcrowdingPercent": 72.77,
    "expectedPolice": 255,
    "realPolice": 239,
    "differenceInPoliceNumbers": 16,
    "top30SelfHarm": true,
    "top30Suicides": true
  },
  {
    "id": "MII179224",
    "type": "Casa circondariale",
    "municipality": "Perugia",
    "region": "Umbria",
    "suicides": 0,
    "attemptedSuicides": 28,
    "selfHarm": 0,
    "regulatoryRooms": 53,
    "nonRegulatoryRooms": 0,
    "totalPrisoners": 82,
    "overcrowdingAbsolute": 29,
    "overcrowdingPercent": 54.72,
    "expectedPolice": 44,
    "realPolice": 44,
    "differenceInPoliceNumbers": 0,
    "top30SelfHarm": true,
    "top30Suicides": false
  },
  {
    "id": "MII178659",
    "type": "Casa di reclusìone",
    "municipality": "Roma",
    "region": "Lazio",
    "suicides": 1,
    "attemptedSuicides": 26,
    "selfHarm": 199,
    "regulatoryRooms": 45,
    "nonRegulatoryRooms": 3,
    "totalPrisoners": 81,
    "overcrowdingAbsolute": 36,
    "overcrowdingPercent": 80,
    "expectedPolice": 828,
    "realPolice": 679,
    "differenceInPoliceNumbers": 149,
    "top30SelfHarm": true,
    "top30Suicides": true
  },
  {
    "id": "MII178003",
    "type": "Casa di reclusìone",
    "municipality": "Ancona",
    "region": "Marche",
    "suicides": 1,
    "attemptedSuicides": 24,
    "selfHarm": 198,
    "regulatoryRooms": 1624,
    "nonRegulatoryRooms": 266,
    "totalPrisoners": 2150,
    "overcrowdingAbsolute": 526,
    "overcrowdingPercent": 32.39,
    "expectedPolice": 184,
    "realPolice": 180,
    "differenceInPoliceNumbers": 4,
    "top30SelfHarm": true,
    "top30Suicides": true
  },
  {
    "id": "MII178045",
    "type": "Casa circondariale",
    "municipality": "Frosìnone",
    "region": "Lazio",
    "suicides": 0,
    "attemptedSuicides": 24,
    "selfHarm": 0,
    "regulatoryRooms": 46,
    "nonRegulatoryRooms": 1,
    "totalPrisoners": 81,
    "overcrowdingAbsolute": 35,
    "overcrowdingPercent": 76.09,
    "expectedPolice": 222,
    "realPolice": 223,
    "differenceInPoliceNumbers": -1,
    "top30SelfHarm": false,
    "top30Suicides": true
  },
  {
    "id": "MII173784",
    "type": "Casa circondariale",
    "municipality": "Taranto",
    "region": "Puglia",
    "suicides": 0,
    "attemptedSuicides": 23,
    "selfHarm": 0,
    "regulatoryRooms": 272,
    "nonRegulatoryRooms": 7,
    "totalPrisoners": 379,
    "overcrowdingAbsolute": 107,
    "overcrowdingPercent": 39.34,
    "expectedPolice": 205,
    "realPolice": 189,
    "differenceInPoliceNumbers": 16,
    "top30SelfHarm": false,
    "top30Suicides": true
  },
  {
    "id": "MII179830",
    "type": "Casa circondariale",
    "municipality": "Pisa",
    "region": "Toscana",
    "suicides": 1,
    "attemptedSuicides": 22,
    "selfHarm": 0,
    "regulatoryRooms": 53,
    "nonRegulatoryRooms": 0,
    "totalPrisoners": 73,
    "overcrowdingAbsolute": 20,
    "overcrowdingPercent": 37.74,
    "expectedPolice": 31,
    "realPolice": 36,
    "differenceInPoliceNumbers": -5,
    "top30SelfHarm": true,
    "top30Suicides": false
  },
  {
    "id": "MII181678",
    "type": "Casa circondariale",
    "municipality": "Genova",
    "region": "Liguria",
    "suicides": 3,
    "attemptedSuicides": 21,
    "selfHarm": 370,
    "regulatoryRooms": 295,
    "nonRegulatoryRooms": 6,
    "totalPrisoners": 525,
    "overcrowdingAbsolute": 230,
    "overcrowdingPercent": 77.97,
    "expectedPolice": 21,
    "realPolice": 32,
    "differenceInPoliceNumbers": -11,
    "top30SelfHarm": true,
    "top30Suicides": true
  },
  {
    "id": "MII181371",
    "type": "Casa circondariale",
    "municipality": "Cremona",
    "region": "Lombardia",
    "suicides": 1,
    "attemptedSuicides": 21,
    "selfHarm": 279,
    "regulatoryRooms": 319,
    "nonRegulatoryRooms": 1,
    "totalPrisoners": 589,
    "overcrowdingAbsolute": 270,
    "overcrowdingPercent": 84.64,
    "expectedPolice": 95,
    "realPolice": 68,
    "differenceInPoliceNumbers": 27,
    "top30SelfHarm": true,
    "top30Suicides": true
  },
  {
    "id": "MII181385",
    "type": "Casa circondariale",
    "municipality": "Piacenza",
    "region": "Emilia Romagna",
    "suicides": 0,
    "attemptedSuicides": 0,
    "selfHarm": 168,
    "regulatoryRooms": 152,
    "nonRegulatoryRooms": 33,
    "totalPrisoners": 199,
    "overcrowdingAbsolute": 47,
    "overcrowdingPercent": 30.92,
    "expectedPolice": 341,
    "realPolice": 286,
    "differenceInPoliceNumbers": 55,
    "top30SelfHarm": true,
    "top30Suicides": false
  },
  {
    "id": "MII181918",
    "type": "Casa circondariale",
    "municipality": "Ivrea",
    "region": "Piemonte",
    "suicides": 0,
    "attemptedSuicides": 0,
    "selfHarm": 165,
    "regulatoryRooms": 265,
    "nonRegulatoryRooms": 2,
    "totalPrisoners": 377,
    "overcrowdingAbsolute": 112,
    "overcrowdingPercent": 42.26,
    "expectedPolice": 60,
    "realPolice": 45,
    "differenceInPoliceNumbers": 15,
    "top30SelfHarm": true,
    "top30Suicides": false
  },
  {
    "id": "MII173301",
    "type": "Casa circondariale",
    "municipality": "Monza",
    "region": "Lombardia",
    "suicides": 1,
    "attemptedSuicides": 0,
    "selfHarm": 161,
    "regulatoryRooms": 243,
    "nonRegulatoryRooms": 20,
    "totalPrisoners": 320,
    "overcrowdingAbsolute": 77,
    "overcrowdingPercent": 31.69,
    "expectedPolice": 164,
    "realPolice": 135,
    "differenceInPoliceNumbers": 29,
    "top30SelfHarm": true,
    "top30Suicides": false
  },
  {
    "id": "MII181691",
    "type": "Casa circondariale",
    "municipality": "Busto Arsìzio",
    "region": "Lombardia",
    "suicides": 0,
    "attemptedSuicides": 0,
    "selfHarm": 141,
    "regulatoryRooms": 364,
    "nonRegulatoryRooms": 22,
    "totalPrisoners": 566,
    "overcrowdingAbsolute": 202,
    "overcrowdingPercent": 55.49,
    "expectedPolice": 112,
    "realPolice": 90,
    "differenceInPoliceNumbers": 22,
    "top30SelfHarm": true,
    "top30Suicides": false
  },
  {
    "id": "MII179988",
    "type": "Casa circondariale",
    "municipality": "Udine",
    "region": "Friuli Venezia Giulia",
    "suicides": 0,
    "attemptedSuicides": 0,
    "selfHarm": 140,
    "regulatoryRooms": 43,
    "nonRegulatoryRooms": 0,
    "totalPrisoners": 55,
    "overcrowdingAbsolute": 12,
    "overcrowdingPercent": 27.91,
    "expectedPolice": 244,
    "realPolice": 233,
    "differenceInPoliceNumbers": 11,
    "top30SelfHarm": true,
    "top30Suicides": false
  },
  {
    "id": "MII172610",
    "type": "Casa di reclusìone",
    "municipality": "Palermo",
    "region": "sìcilia",
    "suicides": 0,
    "attemptedSuicides": 0,
    "selfHarm": 134,
    "regulatoryRooms": 255,
    "nonRegulatoryRooms": 1,
    "totalPrisoners": 361,
    "overcrowdingAbsolute": 106,
    "overcrowdingPercent": 41.57,
    "expectedPolice": 59,
    "realPolice": 63,
    "differenceInPoliceNumbers": -4,
    "top30SelfHarm": true,
    "top30Suicides": false
  },
  {
    "id": "MII181440",
    "type": "Casa circondariale",
    "municipality": "Chieti",
    "region": "Abruzzo",
    "suicides": 0,
    "attemptedSuicides": 0,
    "selfHarm": 0,
    "regulatoryRooms": 240,
    "nonRegulatoryRooms": 13,
    "totalPrisoners": 427,
    "overcrowdingAbsolute": 187,
    "overcrowdingPercent": 77.92,
    "expectedPolice": 0,
    "realPolice": 0,
    "differenceInPoliceNumbers": 0,
    "top30SelfHarm": false,
    "top30Suicides": false
  },
  {
    "id": "MII178027",
    "type": "Casa circondariale",
    "municipality": "Avezzano",
    "region": "Abruzzo",
    "suicides": 0,
    "attemptedSuicides": 0,
    "selfHarm": 0,
    "regulatoryRooms": 411,
    "nonRegulatoryRooms": 3,
    "totalPrisoners": 715,
    "overcrowdingAbsolute": 304,
    "overcrowdingPercent": 73.97,
    "expectedPolice": 44,
    "realPolice": 43,
    "differenceInPoliceNumbers": 1,
    "top30SelfHarm": false,
    "top30Suicides": false
  },
  {
    "id": "MII178035",
    "type": "Casa circondariale",
    "municipality": "L'Aquila",
    "region": "Abruzzo",
    "suicides": 0,
    "attemptedSuicides": 0,
    "selfHarm": 0,
    "regulatoryRooms": 372,
    "nonRegulatoryRooms": 3,
    "totalPrisoners": 563,
    "overcrowdingAbsolute": 191,
    "overcrowdingPercent": 51.34,
    "expectedPolice": 266,
    "realPolice": 242,
    "differenceInPoliceNumbers": 24,
    "top30SelfHarm": false,
    "top30Suicides": false
  },
  {
    "id": "MII177420",
    "type": "Casa di reclusìone",
    "municipality": "Sulmona",
    "region": "Abruzzo",
    "suicides": 0,
    "attemptedSuicides": 0,
    "selfHarm": 0,
    "regulatoryRooms": 918,
    "nonRegulatoryRooms": 18,
    "totalPrisoners": 1308,
    "overcrowdingAbsolute": 390,
    "overcrowdingPercent": 42.48,
    "expectedPolice": 221,
    "realPolice": 199,
    "differenceInPoliceNumbers": 22,
    "top30SelfHarm": false,
    "top30Suicides": false
  },
  {
    "id": "MII177323",
    "type": "Casa circondariale",
    "municipality": "Pescara",
    "region": "Abruzzo",
    "suicides": 0,
    "attemptedSuicides": 0,
    "selfHarm": 0,
    "regulatoryRooms": 438,
    "nonRegulatoryRooms": 63,
    "totalPrisoners": 551,
    "overcrowdingAbsolute": 113,
    "overcrowdingPercent": 25.8,
    "expectedPolice": 342,
    "realPolice": 283,
    "differenceInPoliceNumbers": 59,
    "top30SelfHarm": false,
    "top30Suicides": false
  },
  {
    "id": "MII176788",
    "type": "Casa circondariale",
    "municipality": "Lanciano",
    "region": "Abruzzo",
    "suicides": 0,
    "attemptedSuicides": 0,
    "selfHarm": 0,
    "regulatoryRooms": 141,
    "nonRegulatoryRooms": 0,
    "totalPrisoners": 177,
    "overcrowdingAbsolute": 36,
    "overcrowdingPercent": 25.53,
    "expectedPolice": 951,
    "realPolice": 1115,
    "differenceInPoliceNumbers": -164,
    "top30SelfHarm": false,
    "top30Suicides": false
  },
  {
    "id": "MII158948",
    "type": "Casa circondariale",
    "municipality": "Potenza",
    "region": "Basìlicata",
    "suicides": 0,
    "attemptedSuicides": 0,
    "selfHarm": 0,
    "regulatoryRooms": 159,
    "nonRegulatoryRooms": 2,
    "totalPrisoners": 259,
    "overcrowdingAbsolute": 100,
    "overcrowdingPercent": 62.89,
    "expectedPolice": 206,
    "realPolice": 180,
    "differenceInPoliceNumbers": 26,
    "top30SelfHarm": false,
    "top30Suicides": false
  },
  {
    "id": "MII158895",
    "type": "Casa circondariale",
    "municipality": "Matera",
    "region": "Basìlicata",
    "suicides": 0,
    "attemptedSuicides": 0,
    "selfHarm": 0,
    "regulatoryRooms": 53,
    "nonRegulatoryRooms": 2,
    "totalPrisoners": 72,
    "overcrowdingAbsolute": 19,
    "overcrowdingPercent": 35.85,
    "expectedPolice": 133,
    "realPolice": 113,
    "differenceInPoliceNumbers": 20,
    "top30SelfHarm": false,
    "top30Suicides": false
  },
  {
    "id": "MII158941",
    "type": "Casa di reclusìone",
    "municipality": "Laureana di Borrello",
    "region": "Calabria",
    "suicides": 0,
    "attemptedSuicides": 0,
    "selfHarm": 0,
    "regulatoryRooms": 335,
    "nonRegulatoryRooms": 17,
    "totalPrisoners": 605,
    "overcrowdingAbsolute": 270,
    "overcrowdingPercent": 80.6,
    "expectedPolice": 275,
    "realPolice": 212,
    "differenceInPoliceNumbers": 63,
    "top30SelfHarm": false,
    "top30Suicides": false
  },
  {
    "id": "MII158910",
    "type": "Casa circondariale",
    "municipality": "Locri",
    "region": "Calabria",
    "suicides": 0,
    "attemptedSuicides": 0,
    "selfHarm": 0,
    "regulatoryRooms": 440,
    "nonRegulatoryRooms": 35,
    "totalPrisoners": 716,
    "overcrowdingAbsolute": 276,
    "overcrowdingPercent": 62.73,
    "expectedPolice": 135,
    "realPolice": 110,
    "differenceInPoliceNumbers": 25,
    "top30SelfHarm": false,
    "top30Suicides": false
  },
  {
    "id": "MII158919",
    "type": "Casa circondariale",
    "municipality": "Cosenza",
    "region": "Calabria",
    "suicides": 0,
    "attemptedSuicides": 0,
    "selfHarm": 0,
    "regulatoryRooms": 242,
    "nonRegulatoryRooms": 14,
    "totalPrisoners": 355,
    "overcrowdingAbsolute": 113,
    "overcrowdingPercent": 46.69,
    "expectedPolice": 86,
    "realPolice": 99,
    "differenceInPoliceNumbers": -13,
    "top30SelfHarm": false,
    "top30Suicides": false
  },
  {
    "id": "MII158945",
    "type": "Casa circondariale",
    "municipality": "Palmi",
    "region": "Calabria",
    "suicides": 0,
    "attemptedSuicides": 0,
    "selfHarm": 0,
    "regulatoryRooms": 53,
    "nonRegulatoryRooms": 0,
    "totalPrisoners": 77,
    "overcrowdingAbsolute": 24,
    "overcrowdingPercent": 45.28,
    "expectedPolice": 37,
    "realPolice": 31,
    "differenceInPoliceNumbers": 6,
    "top30SelfHarm": false,
    "top30Suicides": false
  },
  {
    "id": "MII152284",
    "type": "Casa circondariale",
    "municipality": "Crotone",
    "region": "Calabria",
    "suicides": 0,
    "attemptedSuicides": 0,
    "selfHarm": 0,
    "regulatoryRooms": 197,
    "nonRegulatoryRooms": 18,
    "totalPrisoners": 277,
    "overcrowdingAbsolute": 80,
    "overcrowdingPercent": 40.61,
    "expectedPolice": 214,
    "realPolice": 188,
    "differenceInPoliceNumbers": 26,
    "top30SelfHarm": false,
    "top30Suicides": false
  },
  {
    "id": "MII158924",
    "type": "Casa circondariale",
    "municipality": "Castrovillari",
    "region": "Calabria",
    "suicides": 0,
    "attemptedSuicides": 0,
    "selfHarm": 0,
    "regulatoryRooms": 276,
    "nonRegulatoryRooms": 28,
    "totalPrisoners": 384,
    "overcrowdingAbsolute": 108,
    "overcrowdingPercent": 39.13,
    "expectedPolice": 185,
    "realPolice": 163,
    "differenceInPoliceNumbers": 22,
    "top30SelfHarm": false,
    "top30Suicides": false
  },
  {
    "id": "MII158944",
    "type": "Casa circondariale",
    "municipality": "Paola",
    "region": "Calabria",
    "suicides": 1,
    "attemptedSuicides": 0,
    "selfHarm": 0,
    "regulatoryRooms": 230,
    "nonRegulatoryRooms": 42,
    "totalPrisoners": 302,
    "overcrowdingAbsolute": 72,
    "overcrowdingPercent": 31.3,
    "expectedPolice": 84,
    "realPolice": 69,
    "differenceInPoliceNumbers": 15,
    "top30SelfHarm": false,
    "top30Suicides": false
  },
  {
    "id": "MII157783",
    "type": "Casa di reclusìone",
    "municipality": "Corigliano-Rossano",
    "region": "Calabria",
    "suicides": 1,
    "attemptedSuicides": 0,
    "selfHarm": 0,
    "regulatoryRooms": 515,
    "nonRegulatoryRooms": 6,
    "totalPrisoners": 673,
    "overcrowdingAbsolute": 158,
    "overcrowdingPercent": 30.68,
    "expectedPolice": 175,
    "realPolice": 167,
    "differenceInPoliceNumbers": 8,
    "top30SelfHarm": false,
    "top30Suicides": false
  },
  {
    "id": "MII176719",
    "type": "Casa circondariale",
    "municipality": "Avellino",
    "region": "Campania",
    "suicides": 0,
    "attemptedSuicides": 0,
    "selfHarm": 0,
    "regulatoryRooms": 276,
    "nonRegulatoryRooms": 4,
    "totalPrisoners": 455,
    "overcrowdingAbsolute": 179,
    "overcrowdingPercent": 64.86,
    "expectedPolice": 762,
    "realPolice": 693,
    "differenceInPoliceNumbers": 69,
    "top30SelfHarm": false,
    "top30Suicides": false
  },
  {
    "id": "MII176743",
    "type": "Casa circondariale",
    "municipality": "Benevento",
    "region": "Campania",
    "suicides": 1,
    "attemptedSuicides": 0,
    "selfHarm": 0,
    "regulatoryRooms": 156,
    "nonRegulatoryRooms": 1,
    "totalPrisoners": 249,
    "overcrowdingAbsolute": 93,
    "overcrowdingPercent": 59.62,
    "expectedPolice": 139,
    "realPolice": 109,
    "differenceInPoliceNumbers": 30,
    "top30SelfHarm": false,
    "top30Suicides": false
  },
  {
    "id": "MII176424",
    "type": "Casa di reclusìone",
    "municipality": "Sant'Angelo dei Lombardi",
    "region": "Campania",
    "suicides": 0,
    "attemptedSuicides": 0,
    "selfHarm": 0,
    "regulatoryRooms": 37,
    "nonRegulatoryRooms": 0,
    "totalPrisoners": 50,
    "overcrowdingAbsolute": 13,
    "overcrowdingPercent": 35.14,
    "expectedPolice": 129,
    "realPolice": 99,
    "differenceInPoliceNumbers": 30,
    "top30SelfHarm": false,
    "top30Suicides": false
  },
  {
    "id": "MII176714",
    "type": "Casa circondariale",
    "municipality": "Salerno",
    "region": "Campania",
    "suicides": 1,
    "attemptedSuicides": 0,
    "selfHarm": 0,
    "regulatoryRooms": 416,
    "nonRegulatoryRooms": 17,
    "totalPrisoners": 529,
    "overcrowdingAbsolute": 113,
    "overcrowdingPercent": 27.16,
    "expectedPolice": 460,
    "realPolice": 446,
    "differenceInPoliceNumbers": 14,
    "top30SelfHarm": false,
    "top30Suicides": false
  },
  {
    "id": "MII180380",
    "type": "Casa circondariale",
    "municipality": "Ravenna",
    "region": "Emilia Romagna",
    "suicides": 0,
    "attemptedSuicides": 0,
    "selfHarm": 0,
    "regulatoryRooms": 226,
    "nonRegulatoryRooms": 3,
    "totalPrisoners": 447,
    "overcrowdingAbsolute": 221,
    "overcrowdingPercent": 97.79,
    "expectedPolice": 90,
    "realPolice": 83,
    "differenceInPoliceNumbers": 7,
    "top30SelfHarm": false,
    "top30Suicides": false
  },
  {
    "id": "MII180487",
    "type": "Casa di reclusìone",
    "municipality": "Castelfranco Emilia",
    "region": "Emilia Romagna",
    "suicides": 0,
    "attemptedSuicides": 0,
    "selfHarm": 0,
    "regulatoryRooms": 44,
    "nonRegulatoryRooms": 0,
    "totalPrisoners": 70,
    "overcrowdingAbsolute": 26,
    "overcrowdingPercent": 59.09,
    "expectedPolice": 268,
    "realPolice": 250,
    "differenceInPoliceNumbers": 18,
    "top30SelfHarm": false,
    "top30Suicides": false
  },
  {
    "id": "MII173006",
    "type": "Casa circondariale",
    "municipality": "Rimini",
    "region": "Emilia Romagna",
    "suicides": 0,
    "attemptedSuicides": 0,
    "selfHarm": 0,
    "regulatoryRooms": 26,
    "nonRegulatoryRooms": 0,
    "totalPrisoners": 38,
    "overcrowdingAbsolute": 12,
    "overcrowdingPercent": 46.15,
    "expectedPolice": 120,
    "realPolice": 103,
    "differenceInPoliceNumbers": 17,
    "top30SelfHarm": false,
    "top30Suicides": false
  },
  {
    "id": "MII180437",
    "type": "Casa circondariale",
    "municipality": "Ferrara",
    "region": "Emilia Romagna",
    "suicides": 1,
    "attemptedSuicides": 0,
    "selfHarm": 0,
    "regulatoryRooms": 99,
    "nonRegulatoryRooms": 0,
    "totalPrisoners": 125,
    "overcrowdingAbsolute": 26,
    "overcrowdingPercent": 26.26,
    "expectedPolice": 0,
    "realPolice": 0,
    "differenceInPoliceNumbers": 0,
    "top30SelfHarm": false,
    "top30Suicides": false
  },
  {
    "id": "MII179981",
    "type": "Casa circondariale",
    "municipality": "Gorizia",
    "region": "Friuli Venezia Giulia",
    "suicides": 0,
    "attemptedSuicides": 0,
    "selfHarm": 0,
    "regulatoryRooms": 244,
    "nonRegulatoryRooms": 0,
    "totalPrisoners": 396,
    "overcrowdingAbsolute": 152,
    "overcrowdingPercent": 62.3,
    "expectedPolice": 80,
    "realPolice": 97,
    "differenceInPoliceNumbers": -17,
    "top30SelfHarm": false,
    "top30Suicides": false
  },
  {
    "id": "MII179290",
    "type": "Casa circondariale",
    "municipality": "Civitavecchia",
    "region": "Lazio",
    "suicides": 0,
    "attemptedSuicides": 0,
    "selfHarm": 0,
    "regulatoryRooms": 77,
    "nonRegulatoryRooms": 0,
    "totalPrisoners": 134,
    "overcrowdingAbsolute": 57,
    "overcrowdingPercent": 74.03,
    "expectedPolice": 45,
    "realPolice": 41,
    "differenceInPoliceNumbers": 4,
    "top30SelfHarm": false,
    "top30Suicides": false
  },
  {
    "id": "MII178148",
    "type": "Casa circondariale",
    "municipality": "Velletri",
    "region": "Lazio",
    "suicides": 0,
    "attemptedSuicides": 0,
    "selfHarm": 0,
    "regulatoryRooms": 97,
    "nonRegulatoryRooms": 3,
    "totalPrisoners": 157,
    "overcrowdingAbsolute": 60,
    "overcrowdingPercent": 61.86,
    "expectedPolice": 53,
    "realPolice": 44,
    "differenceInPoliceNumbers": 9,
    "top30SelfHarm": false,
    "top30Suicides": false
  },
  {
    "id": "MII178672",
    "type": "Casa circondariale",
    "municipality": "Roma",
    "region": "Lazio",
    "suicides": 0,
    "attemptedSuicides": 0,
    "selfHarm": 0,
    "regulatoryRooms": 86,
    "nonRegulatoryRooms": 0,
    "totalPrisoners": 125,
    "overcrowdingAbsolute": 39,
    "overcrowdingPercent": 45.35,
    "expectedPolice": 166,
    "realPolice": 152,
    "differenceInPoliceNumbers": 14,
    "top30SelfHarm": false,
    "top30Suicides": false
  },
  {
    "id": "MII178085",
    "type": "Casa circondariale",
    "municipality": "Latina",
    "region": "Lazio",
    "suicides": 0,
    "attemptedSuicides": 0,
    "selfHarm": 0,
    "regulatoryRooms": 126,
    "nonRegulatoryRooms": 0,
    "totalPrisoners": 181,
    "overcrowdingAbsolute": 55,
    "overcrowdingPercent": 43.65,
    "expectedPolice": 154,
    "realPolice": 144,
    "differenceInPoliceNumbers": 10,
    "top30SelfHarm": false,
    "top30Suicides": false
  },
  {
    "id": "MII178115",
    "type": "Casa circondariale",
    "municipality": "Rieti",
    "region": "Lazio",
    "suicides": 1,
    "attemptedSuicides": 0,
    "selfHarm": 0,
    "regulatoryRooms": 132,
    "nonRegulatoryRooms": 7,
    "totalPrisoners": 184,
    "overcrowdingAbsolute": 52,
    "overcrowdingPercent": 39.39,
    "expectedPolice": 423,
    "realPolice": 368,
    "differenceInPoliceNumbers": 55,
    "top30SelfHarm": false,
    "top30Suicides": false
  },
  {
    "id": "MII179299",
    "type": "Casa di reclusìone",
    "municipality": "Civitavecchia",
    "region": "Lazio",
    "suicides": 0,
    "attemptedSuicides": 0,
    "selfHarm": 0,
    "regulatoryRooms": 119,
    "nonRegulatoryRooms": 24,
    "totalPrisoners": 153,
    "overcrowdingAbsolute": 34,
    "overcrowdingPercent": 28.57,
    "expectedPolice": 151,
    "realPolice": 131,
    "differenceInPoliceNumbers": 20,
    "top30SelfHarm": false,
    "top30Suicides": false
  },
  {
    "id": "MII181645",
    "type": "Casa di reclusìone",
    "municipality": "Chiavari",
    "region": "Liguria",
    "suicides": 0,
    "attemptedSuicides": 0,
    "selfHarm": 0,
    "regulatoryRooms": 357,
    "nonRegulatoryRooms": 46,
    "totalPrisoners": 550,
    "overcrowdingAbsolute": 193,
    "overcrowdingPercent": 54.06,
    "expectedPolice": 199,
    "realPolice": 173,
    "differenceInPoliceNumbers": 26,
    "top30SelfHarm": false,
    "top30Suicides": false
  },
  {
    "id": "MII181681",
    "type": "Casa circondariale",
    "municipality": "Genova",
    "region": "Liguria",
    "suicides": 0,
    "attemptedSuicides": 0,
    "selfHarm": 0,
    "regulatoryRooms": 259,
    "nonRegulatoryRooms": 8,
    "totalPrisoners": 387,
    "overcrowdingAbsolute": 128,
    "overcrowdingPercent": 49.42,
    "expectedPolice": 27,
    "realPolice": 28,
    "differenceInPoliceNumbers": -1,
    "top30SelfHarm": false,
    "top30Suicides": false
  },
  {
    "id": "MII181891",
    "type": "Casa circondariale",
    "municipality": "Imperia",
    "region": "Liguria",
    "suicides": 2,
    "attemptedSuicides": 0,
    "selfHarm": 0,
    "regulatoryRooms": 256,
    "nonRegulatoryRooms": 0,
    "totalPrisoners": 336,
    "overcrowdingAbsolute": 80,
    "overcrowdingPercent": 31.25,
    "expectedPolice": 127,
    "realPolice": 111,
    "differenceInPoliceNumbers": 16,
    "top30SelfHarm": false,
    "top30Suicides": false
  },
  {
    "id": "MII181417",
    "type": "Casa di reclusìone",
    "municipality": "Bollate",
    "region": "Lombardia",
    "suicides": 0,
    "attemptedSuicides": 0,
    "selfHarm": 0,
    "regulatoryRooms": 503,
    "nonRegulatoryRooms": 21,
    "totalPrisoners": 842,
    "overcrowdingAbsolute": 339,
    "overcrowdingPercent": 67.4,
    "expectedPolice": 224,
    "realPolice": 192,
    "differenceInPoliceNumbers": 32,
    "top30SelfHarm": false,
    "top30Suicides": false
  },
  {
    "id": "MII181625",
    "type": "Casa circondariale",
    "municipality": "Mantova",
    "region": "Lombardia",
    "suicides": 0,
    "attemptedSuicides": 0,
    "selfHarm": 0,
    "regulatoryRooms": 52,
    "nonRegulatoryRooms": 1,
    "totalPrisoners": 85,
    "overcrowdingAbsolute": 33,
    "overcrowdingPercent": 63.46,
    "expectedPolice": 130,
    "realPolice": 119,
    "differenceInPoliceNumbers": 11,
    "top30SelfHarm": false,
    "top30Suicides": false
  },
  {
    "id": "MII181392",
    "type": "Casa di reclusìone",
    "municipality": "Opera",
    "region": "Lombardia",
    "suicides": 0,
    "attemptedSuicides": 0,
    "selfHarm": 0,
    "regulatoryRooms": 71,
    "nonRegulatoryRooms": 1,
    "totalPrisoners": 113,
    "overcrowdingAbsolute": 42,
    "overcrowdingPercent": 59.15,
    "expectedPolice": 188,
    "realPolice": 157,
    "differenceInPoliceNumbers": 31,
    "top30SelfHarm": false,
    "top30Suicides": false
  },
  {
    "id": "MII173237",
    "type": "Casa circondariale",
    "municipality": "Lodi",
    "region": "Lombardia",
    "suicides": 0,
    "attemptedSuicides": 0,
    "selfHarm": 0,
    "regulatoryRooms": 124,
    "nonRegulatoryRooms": 7,
    "totalPrisoners": 171,
    "overcrowdingAbsolute": 47,
    "overcrowdingPercent": 37.9,
    "expectedPolice": 581,
    "realPolice": 674,
    "differenceInPoliceNumbers": -93,
    "top30SelfHarm": false,
    "top30Suicides": false
  },
  {
    "id": "MII181358",
    "type": "Casa di reclusìone",
    "municipality": "Brescia",
    "region": "Lombardia",
    "suicides": 0,
    "attemptedSuicides": 0,
    "selfHarm": 0,
    "regulatoryRooms": 561,
    "nonRegulatoryRooms": 0,
    "totalPrisoners": 759,
    "overcrowdingAbsolute": 198,
    "overcrowdingPercent": 35.29,
    "expectedPolice": 149,
    "realPolice": 124,
    "differenceInPoliceNumbers": 25,
    "top30SelfHarm": false,
    "top30Suicides": false
  },
  {
    "id": "MII173265",
    "type": "Casa circondariale",
    "municipality": "Lecco",
    "region": "Lombardia",
    "suicides": 0,
    "attemptedSuicides": 0,
    "selfHarm": 0,
    "regulatoryRooms": 61,
    "nonRegulatoryRooms": 0,
    "totalPrisoners": 82,
    "overcrowdingAbsolute": 21,
    "overcrowdingPercent": 34.43,
    "expectedPolice": 157,
    "realPolice": 139,
    "differenceInPoliceNumbers": 18,
    "top30SelfHarm": false,
    "top30Suicides": false
  },
  {
    "id": "MII181407",
    "type": "Casa circondariale",
    "municipality": "Milano",
    "region": "Lombardia",
    "suicides": 0,
    "attemptedSuicides": 0,
    "selfHarm": 0,
    "regulatoryRooms": 88,
    "nonRegulatoryRooms": 0,
    "totalPrisoners": 118,
    "overcrowdingAbsolute": 30,
    "overcrowdingPercent": 34.09,
    "expectedPolice": 91,
    "realPolice": 71,
    "differenceInPoliceNumbers": 20,
    "top30SelfHarm": false,
    "top30Suicides": false
  },
  {
    "id": "MII181820",
    "type": "Casa di reclusìone",
    "municipality": "Vigevano",
    "region": "Lombardia",
    "suicides": 1,
    "attemptedSuicides": 0,
    "selfHarm": 0,
    "regulatoryRooms": 103,
    "nonRegulatoryRooms": 4,
    "totalPrisoners": 131,
    "overcrowdingAbsolute": 28,
    "overcrowdingPercent": 27.18,
    "expectedPolice": 119,
    "realPolice": 94,
    "differenceInPoliceNumbers": 25,
    "top30SelfHarm": false,
    "top30Suicides": false
  },
  {
    "id": "MII172580",
    "type": "Casa di reclusìone",
    "municipality": "Monte Giberto",
    "region": "Marche",
    "suicides": 0,
    "attemptedSuicides": 0,
    "selfHarm": 0,
    "regulatoryRooms": 422,
    "nonRegulatoryRooms": 0,
    "totalPrisoners": 572,
    "overcrowdingAbsolute": 150,
    "overcrowdingPercent": 35.55,
    "expectedPolice": 206,
    "realPolice": 169,
    "differenceInPoliceNumbers": 37,
    "top30SelfHarm": false,
    "top30Suicides": false
  },
  {
    "id": "MII178141",
    "type": "Casa di reclusìone",
    "municipality": "Fossombrone",
    "region": "Marche",
    "suicides": 0,
    "attemptedSuicides": 0,
    "selfHarm": 0,
    "regulatoryRooms": 174,
    "nonRegulatoryRooms": 8,
    "totalPrisoners": 231,
    "overcrowdingAbsolute": 57,
    "overcrowdingPercent": 32.76,
    "expectedPolice": 215,
    "realPolice": 218,
    "differenceInPoliceNumbers": -3,
    "top30SelfHarm": false,
    "top30Suicides": false
  },
  {
    "id": "MII177996",
    "type": "Casa circondariale",
    "municipality": "Ancona",
    "region": "Marche",
    "suicides": 0,
    "attemptedSuicides": 0,
    "selfHarm": 0,
    "regulatoryRooms": 1142,
    "nonRegulatoryRooms": 14,
    "totalPrisoners": 1474,
    "overcrowdingAbsolute": 332,
    "overcrowdingPercent": 29.07,
    "expectedPolice": 186,
    "realPolice": 156,
    "differenceInPoliceNumbers": 30,
    "top30SelfHarm": false,
    "top30Suicides": false
  },
  {
    "id": "MII176703",
    "type": "Casa circondariale",
    "municipality": "Larino",
    "region": "Molise",
    "suicides": 0,
    "attemptedSuicides": 0,
    "selfHarm": 0,
    "regulatoryRooms": 49,
    "nonRegulatoryRooms": 1,
    "totalPrisoners": 74,
    "overcrowdingAbsolute": 25,
    "overcrowdingPercent": 51.02,
    "expectedPolice": 572,
    "realPolice": 590,
    "differenceInPoliceNumbers": -18,
    "top30SelfHarm": false,
    "top30Suicides": false
  },
  {
    "id": "MII176749",
    "type": "Casa circondariale",
    "municipality": "Campobasso",
    "region": "Molise",
    "suicides": 0,
    "attemptedSuicides": 0,
    "selfHarm": 0,
    "regulatoryRooms": 363,
    "nonRegulatoryRooms": 55,
    "totalPrisoners": 461,
    "overcrowdingAbsolute": 98,
    "overcrowdingPercent": 27,
    "expectedPolice": 209,
    "realPolice": 227,
    "differenceInPoliceNumbers": -18,
    "top30SelfHarm": false,
    "top30Suicides": false
  },
  {
    "id": "MII181839",
    "type": "Casa circondariale",
    "municipality": "Novara",
    "region": "Piemonte",
    "suicides": 1,
    "attemptedSuicides": 0,
    "selfHarm": 0,
    "regulatoryRooms": 58,
    "nonRegulatoryRooms": 0,
    "totalPrisoners": 91,
    "overcrowdingAbsolute": 33,
    "overcrowdingPercent": 56.9,
    "expectedPolice": 72,
    "realPolice": 72,
    "differenceInPoliceNumbers": 0,
    "top30SelfHarm": false,
    "top30Suicides": false
  },
  {
    "id": "MII182440",
    "type": "Casa di reclusìone",
    "municipality": "Saluzzo",
    "region": "Piemonte",
    "suicides": 1,
    "attemptedSuicides": 0,
    "selfHarm": 0,
    "regulatoryRooms": 702,
    "nonRegulatoryRooms": 232,
    "totalPrisoners": 1072,
    "overcrowdingAbsolute": 370,
    "overcrowdingPercent": 52.71,
    "expectedPolice": 194,
    "realPolice": 179,
    "differenceInPoliceNumbers": 15,
    "top30SelfHarm": false,
    "top30Suicides": false
  },
  {
    "id": "MII181934",
    "type": "Casa di reclusìone",
    "municipality": "Fossano",
    "region": "Piemonte",
    "suicides": 0,
    "attemptedSuicides": 0,
    "selfHarm": 0,
    "regulatoryRooms": 283,
    "nonRegulatoryRooms": 25,
    "totalPrisoners": 356,
    "overcrowdingAbsolute": 73,
    "overcrowdingPercent": 25.8,
    "expectedPolice": 74,
    "realPolice": 69,
    "differenceInPoliceNumbers": 5,
    "top30SelfHarm": false,
    "top30Suicides": false
  },
  {
    "id": "MII174686",
    "type": "Casa di reclusìone",
    "municipality": "Trani",
    "region": "Puglia",
    "suicides": 0,
    "attemptedSuicides": 0,
    "selfHarm": 0,
    "regulatoryRooms": 49,
    "nonRegulatoryRooms": 0,
    "totalPrisoners": 85,
    "overcrowdingAbsolute": 36,
    "overcrowdingPercent": 73.47,
    "expectedPolice": 296,
    "realPolice": 281,
    "differenceInPoliceNumbers": 15,
    "top30SelfHarm": false,
    "top30Suicides": false
  },
  {
    "id": "MII173341",
    "type": "Casa circondariale",
    "municipality": "Assemini",
    "region": "Sardegna",
    "suicides": 3,
    "attemptedSuicides": 0,
    "selfHarm": 0,
    "regulatoryRooms": 376,
    "nonRegulatoryRooms": 3,
    "totalPrisoners": 592,
    "overcrowdingAbsolute": 216,
    "overcrowdingPercent": 57.45,
    "expectedPolice": 258,
    "realPolice": 234,
    "differenceInPoliceNumbers": 24,
    "top30SelfHarm": false,
    "top30Suicides": false
  },
  {
    "id": "MII181434",
    "type": "Casa di reclusìone",
    "municipality": "Alghero",
    "region": "Sardegna",
    "suicides": 0,
    "attemptedSuicides": 0,
    "selfHarm": 0,
    "regulatoryRooms": 394,
    "nonRegulatoryRooms": 4,
    "totalPrisoners": 514,
    "overcrowdingAbsolute": 120,
    "overcrowdingPercent": 30.46,
    "expectedPolice": 41,
    "realPolice": 43,
    "differenceInPoliceNumbers": -2,
    "top30SelfHarm": false,
    "top30Suicides": false
  },
  {
    "id": "MII159069",
    "type": "Casa circondariale",
    "municipality": "Barcellona Pozzo di Gotto",
    "region": "sìcilia",
    "suicides": 0,
    "attemptedSuicides": 0,
    "selfHarm": 0,
    "regulatoryRooms": 53,
    "nonRegulatoryRooms": 0,
    "totalPrisoners": 103,
    "overcrowdingAbsolute": 50,
    "overcrowdingPercent": 94.34,
    "expectedPolice": 131,
    "realPolice": 112,
    "differenceInPoliceNumbers": 19,
    "top30SelfHarm": false,
    "top30Suicides": false
  },
  {
    "id": "MII172814",
    "type": "Casa circondariale",
    "municipality": "Sciacca",
    "region": "sìcilia",
    "suicides": 0,
    "attemptedSuicides": 0,
    "selfHarm": 0,
    "regulatoryRooms": 500,
    "nonRegulatoryRooms": 16,
    "totalPrisoners": 950,
    "overcrowdingAbsolute": 450,
    "overcrowdingPercent": 90,
    "expectedPolice": 39,
    "realPolice": 32,
    "differenceInPoliceNumbers": 7,
    "top30SelfHarm": false,
    "top30Suicides": false
  },
  {
    "id": "MII172011",
    "type": "Casa circondariale",
    "municipality": "Motta Sant'Anastasìa",
    "region": "sìcilia",
    "suicides": 0,
    "attemptedSuicides": 0,
    "selfHarm": 0,
    "regulatoryRooms": 95,
    "nonRegulatoryRooms": 0,
    "totalPrisoners": 175,
    "overcrowdingAbsolute": 80,
    "overcrowdingPercent": 84.21,
    "expectedPolice": 145,
    "realPolice": 154,
    "differenceInPoliceNumbers": -9,
    "top30SelfHarm": false,
    "top30Suicides": false
  },
  {
    "id": "MII179945",
    "type": "Casa di reclusìone",
    "municipality": "Noto",
    "region": "sìcilia",
    "suicides": 0,
    "attemptedSuicides": 0,
    "selfHarm": 0,
    "regulatoryRooms": 364,
    "nonRegulatoryRooms": 19,
    "totalPrisoners": 645,
    "overcrowdingAbsolute": 281,
    "overcrowdingPercent": 77.2,
    "expectedPolice": 149,
    "realPolice": 147,
    "differenceInPoliceNumbers": 2,
    "top30SelfHarm": false,
    "top30Suicides": false
  },
  {
    "id": "MII172208",
    "type": "Casa circondariale",
    "municipality": "Piazza Armerina",
    "region": "sìcilia",
    "suicides": 0,
    "attemptedSuicides": 0,
    "selfHarm": 0,
    "regulatoryRooms": 138,
    "nonRegulatoryRooms": 3,
    "totalPrisoners": 235,
    "overcrowdingAbsolute": 97,
    "overcrowdingPercent": 70.29,
    "expectedPolice": 175,
    "realPolice": 132,
    "differenceInPoliceNumbers": 43,
    "top30SelfHarm": false,
    "top30Suicides": false
  },
  {
    "id": "MII160204",
    "type": "Casa circondariale",
    "municipality": "Montalbano Elicona",
    "region": "sìcilia",
    "suicides": 0,
    "attemptedSuicides": 0,
    "selfHarm": 0,
    "regulatoryRooms": 108,
    "nonRegulatoryRooms": 0,
    "totalPrisoners": 173,
    "overcrowdingAbsolute": 65,
    "overcrowdingPercent": 60.19,
    "expectedPolice": 111,
    "realPolice": 106,
    "differenceInPoliceNumbers": 5,
    "top30SelfHarm": false,
    "top30Suicides": false
  },
  {
    "id": "MII172187",
    "type": "Casa circondariale",
    "municipality": "Caltagirone",
    "region": "sìcilia",
    "suicides": 0,
    "attemptedSuicides": 0,
    "selfHarm": 0,
    "regulatoryRooms": 150,
    "nonRegulatoryRooms": 4,
    "totalPrisoners": 240,
    "overcrowdingAbsolute": 90,
    "overcrowdingPercent": 60,
    "expectedPolice": 480,
    "realPolice": 347,
    "differenceInPoliceNumbers": 133,
    "top30SelfHarm": false,
    "top30Suicides": false
  },
  {
    "id": "MII169535",
    "type": "Casa circondariale",
    "municipality": "Motta Sant'Anastasìa",
    "region": "sìcilia",
    "suicides": 0,
    "attemptedSuicides": 0,
    "selfHarm": 0,
    "regulatoryRooms": 294,
    "nonRegulatoryRooms": 42,
    "totalPrisoners": 436,
    "overcrowdingAbsolute": 142,
    "overcrowdingPercent": 48.3,
    "expectedPolice": 297,
    "realPolice": 318,
    "differenceInPoliceNumbers": -21,
    "top30SelfHarm": false,
    "top30Suicides": false
  },
  {
    "id": "MII159314",
    "type": "Casa circondariale",
    "municipality": "Giarre",
    "region": "sìcilia",
    "suicides": 0,
    "attemptedSuicides": 0,
    "selfHarm": 0,
    "regulatoryRooms": 40,
    "nonRegulatoryRooms": 0,
    "totalPrisoners": 55,
    "overcrowdingAbsolute": 15,
    "overcrowdingPercent": 37.5,
    "expectedPolice": 143,
    "realPolice": 132,
    "differenceInPoliceNumbers": 11,
    "top30SelfHarm": false,
    "top30Suicides": false
  },
  {
    "id": "MII172827",
    "type": "Casa circondariale",
    "municipality": "Castelvetrano",
    "region": "sìcilia",
    "suicides": 0,
    "attemptedSuicides": 0,
    "selfHarm": 0,
    "regulatoryRooms": 323,
    "nonRegulatoryRooms": 8,
    "totalPrisoners": 443,
    "overcrowdingAbsolute": 120,
    "overcrowdingPercent": 37.15,
    "expectedPolice": 44,
    "realPolice": 45,
    "differenceInPoliceNumbers": -1,
    "top30SelfHarm": false,
    "top30Suicides": false
  },
  {
    "id": "MII173088",
    "type": "Casa di reclusìone",
    "municipality": "Favignana",
    "region": "sìcilia",
    "suicides": 0,
    "attemptedSuicides": 0,
    "selfHarm": 0,
    "regulatoryRooms": 58,
    "nonRegulatoryRooms": 0,
    "totalPrisoners": 76,
    "overcrowdingAbsolute": 18,
    "overcrowdingPercent": 31.03,
    "expectedPolice": 36,
    "realPolice": 42,
    "differenceInPoliceNumbers": -6,
    "top30SelfHarm": false,
    "top30Suicides": false
  },
  {
    "id": "MII172344",
    "type": "Casa di reclusìone",
    "municipality": "San Cataldo",
    "region": "sìcilia",
    "suicides": 0,
    "attemptedSuicides": 0,
    "selfHarm": 0,
    "regulatoryRooms": 1117,
    "nonRegulatoryRooms": 22,
    "totalPrisoners": 1455,
    "overcrowdingAbsolute": 338,
    "overcrowdingPercent": 30.26,
    "expectedPolice": 317,
    "realPolice": 319,
    "differenceInPoliceNumbers": -2,
    "top30SelfHarm": false,
    "top30Suicides": false
  },
  {
    "id": "MII179818",
    "type": "Casa circondariale",
    "municipality": "Lucca",
    "region": "Toscana",
    "suicides": 0,
    "attemptedSuicides": 0,
    "selfHarm": 0,
    "regulatoryRooms": 15,
    "nonRegulatoryRooms": 0,
    "totalPrisoners": 30,
    "overcrowdingAbsolute": 15,
    "overcrowdingPercent": 100,
    "expectedPolice": 46,
    "realPolice": 48,
    "differenceInPoliceNumbers": -2,
    "top30SelfHarm": false,
    "top30Suicides": false
  },
  {
    "id": "MII179876",
    "type": "Casa di reclusìone",
    "municipality": "Massa",
    "region": "Toscana",
    "suicides": 0,
    "attemptedSuicides": 0,
    "selfHarm": 0,
    "regulatoryRooms": 48,
    "nonRegulatoryRooms": 0,
    "totalPrisoners": 73,
    "overcrowdingAbsolute": 25,
    "overcrowdingPercent": 52.08,
    "expectedPolice": 0,
    "realPolice": 0,
    "differenceInPoliceNumbers": 0,
    "top30SelfHarm": false,
    "top30Suicides": false
  },
  {
    "id": "MII179856",
    "type": "Casa circondariale",
    "municipality": "Livorno",
    "region": "Toscana",
    "suicides": 1,
    "attemptedSuicides": 0,
    "selfHarm": 0,
    "regulatoryRooms": 96,
    "nonRegulatoryRooms": 11,
    "totalPrisoners": 142,
    "overcrowdingAbsolute": 46,
    "overcrowdingPercent": 47.92,
    "expectedPolice": 336,
    "realPolice": 320,
    "differenceInPoliceNumbers": 16,
    "top30SelfHarm": false,
    "top30Suicides": false
  },
  {
    "id": "MII179733",
    "type": "Casa circondariale",
    "municipality": "Massa Marittima",
    "region": "Toscana",
    "suicides": 0,
    "attemptedSuicides": 0,
    "selfHarm": 0,
    "regulatoryRooms": 44,
    "nonRegulatoryRooms": 0,
    "totalPrisoners": 64,
    "overcrowdingAbsolute": 20,
    "overcrowdingPercent": 45.45,
    "expectedPolice": 151,
    "realPolice": 117,
    "differenceInPoliceNumbers": 34,
    "top30SelfHarm": false,
    "top30Suicides": false
  },
  {
    "id": "MII179781",
    "type": "Casa di reclusìone",
    "municipality": "Volterra",
    "region": "Toscana",
    "suicides": 0,
    "attemptedSuicides": 0,
    "selfHarm": 0,
    "regulatoryRooms": 53,
    "nonRegulatoryRooms": 0,
    "totalPrisoners": 76,
    "overcrowdingAbsolute": 23,
    "overcrowdingPercent": 43.4,
    "expectedPolice": 127,
    "realPolice": 114,
    "differenceInPoliceNumbers": 13,
    "top30SelfHarm": false,
    "top30Suicides": false
  },
  {
    "id": "MII179353",
    "type": "Casa di reclusìone",
    "municipality": "San Gimignano",
    "region": "Toscana",
    "suicides": 0,
    "attemptedSuicides": 0,
    "selfHarm": 0,
    "regulatoryRooms": 195,
    "nonRegulatoryRooms": 6,
    "totalPrisoners": 263,
    "overcrowdingAbsolute": 68,
    "overcrowdingPercent": 34.87,
    "expectedPolice": 119,
    "realPolice": 11,
    "differenceInPoliceNumbers": 108,
    "top30SelfHarm": false,
    "top30Suicides": false
  },
  {
    "id": "MII179280",
    "type": "Casa circondariale",
    "municipality": "Arezzo",
    "region": "Toscana",
    "suicides": 0,
    "attemptedSuicides": 0,
    "selfHarm": 0,
    "regulatoryRooms": 37,
    "nonRegulatoryRooms": 0,
    "totalPrisoners": 48,
    "overcrowdingAbsolute": 11,
    "overcrowdingPercent": 29.73,
    "expectedPolice": 416,
    "realPolice": 435,
    "differenceInPoliceNumbers": -19,
    "top30SelfHarm": false,
    "top30Suicides": false
  },
  {
    "id": "MII180458",
    "type": "Casa circondariale",
    "municipality": "Bolzano/Bozen",
    "region": "Trentino",
    "suicides": 0,
    "attemptedSuicides": 0,
    "selfHarm": 0,
    "regulatoryRooms": 279,
    "nonRegulatoryRooms": 0,
    "totalPrisoners": 420,
    "overcrowdingAbsolute": 141,
    "overcrowdingPercent": 50.54,
    "expectedPolice": 255,
    "realPolice": 237,
    "differenceInPoliceNumbers": 18,
    "top30SelfHarm": false,
    "top30Suicides": false
  },
  {
    "id": "MII180476",
    "type": "Casa circondariale",
    "municipality": "Trento",
    "region": "Trentino",
    "suicides": 0,
    "attemptedSuicides": 0,
    "selfHarm": 0,
    "regulatoryRooms": 122,
    "nonRegulatoryRooms": 1,
    "totalPrisoners": 181,
    "overcrowdingAbsolute": 59,
    "overcrowdingPercent": 48.36,
    "expectedPolice": 65,
    "realPolice": 53,
    "differenceInPoliceNumbers": 12,
    "top30SelfHarm": false,
    "top30Suicides": false
  },
  {
    "id": "MII179237",
    "type": "Casa di reclusìone",
    "municipality": "Orvieto",
    "region": "Umbria",
    "suicides": 0,
    "attemptedSuicides": 0,
    "selfHarm": 0,
    "regulatoryRooms": 798,
    "nonRegulatoryRooms": 50,
    "totalPrisoners": 1236,
    "overcrowdingAbsolute": 438,
    "overcrowdingPercent": 54.89,
    "expectedPolice": 206,
    "realPolice": 197,
    "differenceInPoliceNumbers": 9,
    "top30SelfHarm": false,
    "top30Suicides": false
  },
  {
    "id": "MII178501",
    "type": "Casa di reclusìone",
    "municipality": "Spoleto",
    "region": "Umbria",
    "suicides": 0,
    "attemptedSuicides": 0,
    "selfHarm": 0,
    "regulatoryRooms": 135,
    "nonRegulatoryRooms": 0,
    "totalPrisoners": 170,
    "overcrowdingAbsolute": 35,
    "overcrowdingPercent": 25.93,
    "expectedPolice": 185,
    "realPolice": 228,
    "differenceInPoliceNumbers": -43,
    "top30SelfHarm": false,
    "top30Suicides": false
  },
  {
    "id": "MII182919",
    "type": "Casa circondariale",
    "municipality": "Brissogne",
    "region": "Valle d'Aosta",
    "suicides": 0,
    "attemptedSuicides": 0,
    "selfHarm": 0,
    "regulatoryRooms": 535,
    "nonRegulatoryRooms": 0,
    "totalPrisoners": 689,
    "overcrowdingAbsolute": 154,
    "overcrowdingPercent": 28.79,
    "expectedPolice": 243,
    "realPolice": 202,
    "differenceInPoliceNumbers": 41,
    "top30SelfHarm": false,
    "top30Suicides": false
  },
  {
    "id": "MII180415",
    "type": "Casa di reclusìone",
    "municipality": "Padova",
    "region": "Veneto",
    "suicides": 0,
    "attemptedSuicides": 0,
    "selfHarm": 0,
    "regulatoryRooms": 79,
    "nonRegulatoryRooms": 0,
    "totalPrisoners": 134,
    "overcrowdingAbsolute": 55,
    "overcrowdingPercent": 69.62,
    "expectedPolice": 234,
    "realPolice": 197,
    "differenceInPoliceNumbers": 37,
    "top30SelfHarm": false,
    "top30Suicides": false
  },
  {
    "id": "MII180370",
    "type": "Casa circondariale",
    "municipality": "Belluno",
    "region": "Veneto",
    "suicides": 0,
    "attemptedSuicides": 0,
    "selfHarm": 0,
    "regulatoryRooms": 394,
    "nonRegulatoryRooms": 10,
    "totalPrisoners": 580,
    "overcrowdingAbsolute": 186,
    "overcrowdingPercent": 47.21,
    "expectedPolice": 237,
    "realPolice": 201,
    "differenceInPoliceNumbers": 36,
    "top30SelfHarm": false,
    "top30Suicides": false
  },
  {
    "id": "MII180424",
    "type": "Casa circondariale",
    "municipality": "Padova",
    "region": "Veneto",
    "suicides": 1,
    "attemptedSuicides": 0,
    "selfHarm": 0,
    "regulatoryRooms": 52,
    "nonRegulatoryRooms": 0,
    "totalPrisoners": 66,
    "overcrowdingAbsolute": 14,
    "overcrowdingPercent": 26.92,
    "expectedPolice": 280,
    "realPolice": 239,
    "differenceInPoliceNumbers": 41,
    "top30SelfHarm": false,
    "top30Suicides": false
  }
]
